v2dl/__init__.py
v2dl/__main__.py
v2dl/version.py
v2dl/cli/__init__.py
v2dl/cli/account_cli.py
v2dl/cli/option.py
v2dl/common/__init__.py
v2dl/common/config.py
v2dl/common/const.py
v2dl/common/cookies.py
v2dl/common/error.py
v2dl/common/logger.py
v2dl/common/model.py
v2dl/common/utils.py
v2dl/scraper/__init__.py
v2dl/scraper/core.py
v2dl/scraper/downloader.py
v2dl/scraper/manager.py
v2dl/scraper/tools.py
v2dl/scraper/types.py
v2dl/security/__init__.py
v2dl/security/main.py
v2dl/web_bot/__init__.py
v2dl/web_bot/base.py
v2dl/web_bot/drission_bot.py
v2dl/web_bot/get.py
v2dl/web_bot/selenium_bot.py
v2dl-0.4.5.dist-info/METADATA
v2dl-0.4.5.dist-info/WHEEL
v2dl-0.4.5.dist-info/entry_points.txt
v2dl-0.4.5.dist-info/licenses/LICENSE
v2dl-0.4.5.dist-info/RECORD
