Metadata-Version: 2.4
Name: v2dl
Version: 0.4.5
Summary: V2PH downloader
Project-URL: repository, https://github.com/ZhenShuo2021/V2PH-Downloader
Project-URL: homepage, https://github.com/ZhenShuo2021/V2PH-Downloader
Author-email: ZhenShuo2021 <leo01412123@gmail.com>
License:                     GNU GENERAL PUBLIC LICENSE
License-File: LICENSE
Keywords: image-downloader,v2ph,v2ph-downloader,v2ph.com
Classifier: Development Status :: 4 - Beta
Classifier: Environment :: Console
Classifier: License :: OSI Approved :: GNU General Public License v3 (GPLv3)
Classifier: Programming Language :: Python
Classifier: Programming Language :: Python :: 3 :: Only
Classifier: Programming Language :: Python :: 3.10
Classifier: Programming Language :: Python :: 3.11
Classifier: Programming Language :: Python :: 3.12
Classifier: Programming Language :: Python :: 3.13
Classifier: Programming Language :: Python :: Implementation
Classifier: Programming Language :: Python :: Implementation :: CPython
Classifier: Topic :: Multimedia
Requires-Python: >=3.10
Requires-Dist: colorama>=0.4.6
Requires-Dist: drissionpage>=4.1.0.9
Requires-Dist: httpx[http2]>=0.27.2
Requires-Dist: lxml>=5.3.0
Requires-Dist: pathvalidate>=3.2.1
Requires-Dist: pynacl>=1.5.0
Requires-Dist: python-dotenv>=1.0.1
Requires-Dist: pyyaml>=6.0.2
Requires-Dist: questionary>=2.0.1
Provides-Extra: all
Requires-Dist: selenium>=4.27.1; extra == 'all'
